{
  "Siornya/XCPC-algorithm-reference": {
    "lastDate": "2026-06-02T13:00:17Z",
    "boundaryShas": [
      "cd4a656b7733f9591341e4a4192c7731f31a56e0"
    ],
    "add": {
      "YAML": 18,
      "C++": 8022,
      "Markdown": 3519,
      "Python": 35
    },
    "del": {
      "YAML": 0,
      "C++": 5155,
      "Markdown": 132,
      "Python": 35
    }
  },
  "Siornya/nonebot-plugin-R6States": {
    "lastDate": "2026-06-13T07:46:45Z",
    "boundaryShas": [
      "a45366ff2bc4d23de0dce55c2c0148a0c0ec6747"
    ],
    "add": {
      "Markdown": 162,
      "TOML": 77,
      "Python": 2053,
      "YAML": 302,
      "C++": 327
    },
    "del": {
      "Markdown": 47,
      "TOML": 4,
      "Python": 904,
      "YAML": 36,
      "C++": 327
    }
  },
  "Siornya/hexo-theme-columbula": {
    "lastDate": "2026-06-08T18:38:11Z",
    "boundaryShas": [
      "5c2de6381e0984ab0c9b83b47353a89cf6134ac9"
    ],
    "add": {
      "YAML": 89,
      "CSS": 2313,
      "JavaScript": 350,
      "Markdown": 179
    },
    "del": {
      "YAML": 21,
      "CSS": 856,
      "JavaScript": 79,
      "Markdown": 0
    }
  },
  "LONETRAIL-Lab/MilkyWay": {
    "lastDate": "2026-03-27T11:48:12Z",
    "boundaryShas": [
      "e061050cf52be2d5936d3e32e2cdad17b5e38e6d"
    ],
    "add": {
      "C++": 480,
      "C": 554,
      "Markdown": 3,
      "C#": 53
    },
    "del": {
      "C++": 34,
      "C": 27,
      "Markdown": 0,
      "C#": 0
    }
  },
  "LONETRAIL-Lab/Deneb-docs": {
    "lastDate": "2026-05-28T07:37:23Z",
    "boundaryShas": [
      "afa1ed8a684dc4439e87e23aa1168496509de269"
    ],
    "add": {
      "Markdown": 751
    },
    "del": {
      "Markdown": 148
    }
  },
  "Siornya/Siornya-cafe": {
    "lastDate": "2026-06-10T17:55:42Z",
    "boundaryShas": [
      "d0a4c695fe15ae2e4ce427ca869844a35456b446"
    ],
    "add": {
      "TypeScript": 260,
      "Vue": 2148,
      "CSS": 167,
      "HTML": 18,
      "YAML": 38,
      "JSON": 116,
      "Markdown": 94
    },
    "del": {
      "TypeScript": 54,
      "Vue": 819,
      "CSS": 43,
      "HTML": 5,
      "YAML": 0,
      "JSON": 4,
      "Markdown": 0
    }
  },
  "LONETRAIL-Lab/Deneb": {
    "lastDate": "2026-05-28T07:18:26Z",
    "boundaryShas": [
      "dfeca5bebbbd2db202ad14c7c392fb5cdf97eb71"
    ],
    "add": {
      "C++": 802,
      "C": 760,
      "C#": 54,
      "Markdown": 3
    },
    "del": {
      "C++": 223,
      "C": 154,
      "C#": 1,
      "Markdown": 0
    }
  },
  "Siornya/Siornya.github.io": {
    "lastDate": "2026-06-09T18:19:32Z",
    "boundaryShas": [
      "6e945ad93a76e23b35f84606dd7785d9590d5ddd"
    ],
    "add": {
      "Markdown": 6608,
      "YAML": 5364,
      "JSON": 86,
      "JavaScript": 1584
    },
    "del": {
      "Markdown": 2814,
      "YAML": 4212,
      "JSON": 57,
      "JavaScript": 2316
    }
  },
  "Siornya/cafe-crossing": {
    "lastDate": "2026-05-27T08:04:13Z",
    "boundaryShas": [
      "fd656a37bf8d7787408df38a60515b9ec2d88fcc"
    ],
    "add": {
      "HTML": 19,
      "Vue": 1244,
      "CSS": 36,
      "YAML": 77,
      "JSON": 154,
      "Markdown": 54,
      "TypeScript": 127
    },
    "del": {
      "HTML": 6,
      "Vue": 363,
      "CSS": 0,
      "YAML": 1,
      "JSON": 0,
      "Markdown": 0,
      "TypeScript": 2
    }
  },
  "Siornya/StS2-Virtuosa": {
    "lastDate": "2026-03-26T08:49:01Z",
    "boundaryShas": [
      "553703b607005f0b332dc1be7f3f0aab40831c18"
    ],
    "add": {
      "C#": 885,
      "JSON": 163
    },
    "del": {
      "C#": 99,
      "JSON": 52
    }
  },
  "Siornya/not-enough-chaoxing": {
    "lastDate": "2026-06-07T13:57:05Z",
    "boundaryShas": [
      "5966a76e2b0bf07ed4577d1d466bb721d00d61d4"
    ],
    "add": {
      "SQL": 2258,
      "HTML": 31,
      "Vue": 1510,
      "JavaScript": 964,
      "Markdown": 725,
      "TypeScript": 269,
      "JSON": 102,
      "CSS": 174
    },
    "del": {
      "SQL": 678,
      "HTML": 6,
      "Vue": 119,
      "JavaScript": 360,
      "Markdown": 20,
      "TypeScript": 24,
      "JSON": 2,
      "CSS": 4
    }
  },
  "LONETRAIL-Lab/organization-docs": {
    "lastDate": "2026-05-01T05:46:22Z",
    "boundaryShas": [
      "8b8578051e93976adba34e5cfbc3e398d2aac58b"
    ],
    "add": {
      "Markdown": 60
    },
    "del": {
      "Markdown": 2
    }
  },
  "Siornya/Siornya": {
    "lastDate": "2026-06-02T12:28:22Z",
    "boundaryShas": [
      "8e6fd80af29ed888d92a918ebd2d274eb4406c7d"
    ],
    "add": {
      "YAML": 43,
      "Markdown": 65,
      "JavaScript": 357,
      "JSON": 5
    },
    "del": {
      "YAML": 4,
      "Markdown": 16,
      "JavaScript": 9,
      "JSON": 0
    }
  },
  "Siornya/cafe-api": {
    "lastDate": "2026-05-27T03:42:37Z",
    "boundaryShas": [
      "624ae1532ba142cba85ef35f345ba9f96315bb02"
    ],
    "add": {
      "JSON": 74,
      "TypeScript": 118
    },
    "del": {
      "JSON": 1,
      "TypeScript": 0
    }
  },
  "Siornya/feather-bot": {
    "lastDate": "2026-06-13T09:51:25Z",
    "boundaryShas": [
      "cb5fdff46fc64a7063507429236316ab1193883a"
    ],
    "add": {
      "TOML": 29,
      "Markdown": 11,
      "JSON": 920,
      "Python": 1080
    },
    "del": {
      "TOML": 2,
      "Markdown": 0,
      "JSON": 0,
      "Python": 0
    }
  }
}